{
  "code": "603800",
  "name": "洪田股份",
  "fetchTime": "2026-06-18T21:18:34.664528",
  "profile": {
    "name": "洪田股份",
    "code": "603800",
    "fullName": "江苏洪田科技股份有限公司",
    "chairman": "朱开星",
    "legalPerson": "赵伟斌",
    "secretary": "朱开星",
    "industry": "机械设备-专用设备-其他专用机械",
    "industryCSRC": "制造业-专用设备制造业",
    "mainBusiness": "许可项目:特种设备制造(依法须经批准的项目,经相关部门批准后方可开展经营活动,具体经营项目以审批结果为准)一般项目:人工智能基础软件开发;人工智能应用软件开发;电子专用设备制造;电子专用设备销售;半导体器件专用设备制造;半导体器件专用设备销售;新能源原动设备制造;新能源原动设备销售;石油钻采专用设备制造;普通阀门和旋塞制造(不含特种设备制造);锻件及粉末冶金制品制造;通用零部件制造;以自有资金从事投资活动;技术服务、技术开发、技术咨询、技术交流、技术转让、技术推广;技术进出口;货物进出口(除依法须经批准的项目外,凭营业执照依法自主开展经营活动)。",
    "province": "江苏",
    "website": "",
    "description": "    江苏洪田科技股份有限公司(SH603800),是国内高端铜箔装备龙头企业及国内首家掌握并采用“一步法全干法”工艺路线的真空镀膜设备厂商,产品广泛应用于锂电、固态电池、泛半导体、光伏、军工航天、消费电子等多个领域。公司通过“内增外拓”,加快高端制造装备平台型企业布局,加速打造真空镀膜设备全链平台,推动企业实现超精密真空镀膜、光学及半导体等领域的全面布局。",
    "setupDate": "",
    "listDate": "",
    "securityType": "上交所主板A股"
  },
  "financial": [
    {
      "reportDate": "2026-03-31",
      "reportName": "2026一季报",
      "reportType": "一季报",
      "basicEPS": -0.08,
      "dilutedEPS": -0.08,
      "deductEPS": null,
      "bps": 3.802835350288,
      "opsCashPerShare": 0.048659098221,
      "totalRevenue": 117862064.14,
      "totalRevenueYoY": -12.78,
      "totalRevenueQoQ": -1.6,
      "grossProfit": -2234447.0,
      "netProfit": -16020835.19,
      "netProfitYoY": 36.55,
      "netProfitQoQ": 63.53,
      "deductNetProfit": -17405975.26,
      "deductNetProfitYoY": 38.73,
      "deductNetProfitQoQ": 398.87,
      "nonRecurringPnL": 1385140.07,
      "nonRecurringRatio": -8.65,
      "weightedROE": -2.0,
      "deductROE": null,
      "grossMargin": -1.9,
      "netMargin": -16.72,
      "cashToRevenue": 0.09,
      "cashToProfit": 0.74,
      "debtRatio": 62.57,
      "currentRatio": 1.20430509997,
      "quickRatio": 0.745575800455,
      "assetTurnover": 0.047336972685,
      "inventoryTurnoverDays": 439.264097285332,
      "receivableTurnoverDays": 362.015515609734
    },
    {
      "reportDate": "2025-12-31",
      "reportName": "2025年报",
      "reportType": "年报",
      "basicEPS": 0.07,
      "dilutedEPS": 0.07,
      "deductEPS": -0.01,
      "bps": 3.897383760577,
      "opsCashPerShare": 0.768131717452,
      "totalRevenue": 1078772647.45,
      "totalRevenueYoY": -21.46,
      "totalRevenueQoQ": -9.6,
      "grossProfit": 240998033.35,
      "netProfit": 14524996.46,
      "netProfitYoY": -87.58,
      "netProfitQoQ": -84.6,
      "deductNetProfit": -2757992.33,
      "deductNetProfitYoY": -103.55,
      "deductNetProfitQoQ": -104.21,
      "nonRecurringPnL": 17282988.79,
      "nonRecurringRatio": 118.99,
      "weightedROE": 1.78,
      "deductROE": -0.34,
      "grossMargin": 22.34,
      "netMargin": 1.46,
      "cashToRevenue": 0.15,
      "cashToProfit": 0.34,
      "debtRatio": 61.61,
      "currentRatio": 1.226588172606,
      "quickRatio": 0.800994769503,
      "assetTurnover": 0.39880607278,
      "inventoryTurnoverDays": 292.428191249375,
      "receivableTurnoverDays": 178.318914217704
    },
    {
      "reportDate": "2025-09-30",
      "reportName": "2025三季报",
      "reportType": "三季报",
      "basicEPS": 0.3096,
      "dilutedEPS": 0.3096,
      "deductEPS": null,
      "bps": 4.142884656442,
      "opsCashPerShare": 0.32231473351,
      "totalRevenue": 880995160.78,
      "totalRevenueYoY": -16.99,
      "totalRevenueQoQ": 10.77,
      "grossProfit": 221780288.84,
      "netProfit": 62446224.37,
      "netProfitYoY": -26.66,
      "netProfitQoQ": 339.48,
      "deductNetProfit": 43216357.93,
      "deductNetProfitYoY": -22.13,
      "deductNetProfitQoQ": 1206.64,
      "nonRecurringPnL": 19229866.44,
      "nonRecurringRatio": 30.79,
      "weightedROE": 7.46,
      "deductROE": null,
      "grossMargin": 25.17,
      "netMargin": 8.6,
      "cashToRevenue": 0.08,
      "cashToProfit": 0.17,
      "debtRatio": 62.79,
      "currentRatio": 1.387501431867,
      "quickRatio": 0.950991046876,
      "assetTurnover": 0.311508719246,
      "inventoryTurnoverDays": 293.670649169069,
      "receivableTurnoverDays": 171.055516107472
    },
    {
      "reportDate": "2025-06-30",
      "reportName": "2025中报",
      "reportType": "中报",
      "basicEPS": -0.1761,
      "dilutedEPS": -0.1761,
      "deductEPS": -0.206,
      "bps": 3.669847599279,
      "opsCashPerShare": 0.541921150769,
      "totalRevenue": 386344628.65,
      "totalRevenueYoY": -43.4,
      "totalRevenueQoQ": -8.05,
      "grossProfit": 60173718.29,
      "netProfit": -35509849.14,
      "netProfitYoY": -159.16,
      "netProfitQoQ": -65.74,
      "deductNetProfit": -41549703.48,
      "deductNetProfitYoY": -198.71,
      "deductNetProfitQoQ": -120.62,
      "nonRecurringPnL": 6039854.34,
      "nonRecurringRatio": -17.01,
      "weightedROE": -4.5,
      "deductROE": -5.27,
      "grossMargin": 15.58,
      "netMargin": -11.15,
      "cashToRevenue": 0.29,
      "cashToProfit": 0.45,
      "debtRatio": 69.17,
      "currentRatio": 1.274749269458,
      "quickRatio": 0.814081842852,
      "assetTurnover": 0.132501439005,
      "inventoryTurnoverDays": 436.385513425213,
      "receivableTurnoverDays": 262.365933039257
    },
    {
      "reportDate": "2025-03-31",
      "reportName": "2025一季报",
      "reportType": "一季报",
      "basicEPS": -0.13,
      "dilutedEPS": -0.13,
      "deductEPS": null,
      "bps": 3.815305703317,
      "opsCashPerShare": 0.225176923558,
      "totalRevenue": 135126133.69,
      "totalRevenueYoY": -59.91,
      "totalRevenueQoQ": -14.7,
      "grossProfit": 16382592.92,
      "netProfit": -25248698.21,
      "netProfitYoY": -186.72,
      "netProfitQoQ": -46.47,
      "deductNetProfit": -28406744.17,
      "deductNetProfitYoY": -237.66,
      "deductNetProfitQoQ": -63.1,
      "nonRecurringPnL": 3158045.96,
      "nonRecurringRatio": -12.51,
      "weightedROE": -3.14,
      "deductROE": null,
      "grossMargin": 12.12,
      "netMargin": -23.32,
      "cashToRevenue": 0.35,
      "cashToProfit": 0.06,
      "debtRatio": 70.16,
      "currentRatio": 1.297502341865,
      "quickRatio": 0.859253511348,
      "assetTurnover": 0.044788262308,
      "inventoryTurnoverDays": 623.12592117547,
      "receivableTurnoverDays": 397.098828576997
    },
    {
      "reportDate": "2024-12-31",
      "reportName": "2024年报",
      "reportType": "年报",
      "basicEPS": 0.58,
      "dilutedEPS": 0.58,
      "deductEPS": 0.38,
      "bps": 3.93265642274,
      "opsCashPerShare": 0.118781830048,
      "totalRevenue": 1373603914.21,
      "totalRevenueYoY": -38.6,
      "totalRevenueQoQ": -22.77,
      "grossProfit": 326674868.86,
      "netProfit": 116990127.42,
      "netProfitYoY": -42.87,
      "netProfitQoQ": -48.95,
      "deductNetProfit": 77727030.38,
      "deductNetProfitYoY": -47.32,
      "deductNetProfitQoQ": -50.0,
      "nonRecurringPnL": 39263097.04,
      "nonRecurringRatio": 33.56,
      "weightedROE": 14.57,
      "deductROE": 9.68,
      "grossMargin": 23.78,
      "netMargin": 10.34,
      "cashToRevenue": 0.02,
      "cashToProfit": 0.19,
      "debtRatio": 66.78,
      "currentRatio": 1.368800214818,
      "quickRatio": 0.871548078717,
      "assetTurnover": 0.419925200253,
      "inventoryTurnoverDays": 337.179315541146,
      "receivableTurnoverDays": 138.152677779856
    },
    {
      "reportDate": "2024-09-30",
      "reportName": "2024三季报",
      "reportType": "三季报",
      "basicEPS": 0.4175,
      "dilutedEPS": 0.4175,
      "deductEPS": null,
      "bps": 3.788271030433,
      "opsCashPerShare": -0.109030101587,
      "totalRevenue": 1061265800.13,
      "totalRevenueYoY": -30.18,
      "totalRevenueQoQ": -4.45,
      "grossProfit": 236311074.95,
      "netProfit": 85143756.4,
      "netProfitYoY": 40.18,
      "netProfitQoQ": 6.44,
      "deductNetProfit": 55500937.74,
      "deductNetProfitYoY": 16.61,
      "deductNetProfitQoQ": 1.37,
      "nonRecurringPnL": 29642818.66,
      "nonRecurringRatio": 34.82,
      "weightedROE": 10.45,
      "deductROE": null,
      "grossMargin": 22.27,
      "netMargin": 10.11,
      "cashToRevenue": -0.02,
      "cashToProfit": 0.31,
      "debtRatio": 71.95,
      "currentRatio": 1.302415776534,
      "quickRatio": 0.854933087849,
      "assetTurnover": 0.306868059084,
      "inventoryTurnoverDays": 346.812173120261,
      "receivableTurnoverDays": 151.296773706331
    },
    {
      "reportDate": "2024-06-30",
      "reportName": "2024中报",
      "reportType": "中报",
      "basicEPS": 0.2936,
      "dilutedEPS": 0.2936,
      "deductEPS": 0.2059,
      "bps": 3.815843341971,
      "opsCashPerShare": -0.273568713365,
      "totalRevenue": 682622587.89,
      "totalRevenueYoY": -35.51,
      "totalRevenueQoQ": -14.8,
      "grossProfit": 161618944.91,
      "netProfit": 60024570.27,
      "netProfitYoY": 21.31,
      "netProfitQoQ": -0.39,
      "deductNetProfit": 42090967.52,
      "deductNetProfitYoY": 16.01,
      "deductNetProfitQoQ": -7.51,
      "nonRecurringPnL": 17933602.75,
      "nonRecurringRatio": 29.88,
      "weightedROE": 7.39,
      "deductROE": 5.18,
      "grossMargin": 23.68,
      "netMargin": 11.17,
      "cashToRevenue": -0.08,
      "cashToProfit": 0.4,
      "debtRatio": 74.79,
      "currentRatio": 1.299381594514,
      "quickRatio": 0.83279975228,
      "assetTurnover": 0.187437548895,
      "inventoryTurnoverDays": 393.277778646922,
      "receivableTurnoverDays": 156.911714515859
    },
    {
      "reportDate": "2024-03-31",
      "reportName": "2024一季报",
      "reportType": "一季报",
      "basicEPS": 0.1413,
      "dilutedEPS": 0.1413,
      "deductEPS": null,
      "bps": 3.825376810048,
      "opsCashPerShare": -0.158380660433,
      "totalRevenue": 337052539.27,
      "totalRevenueYoY": -13.47,
      "totalRevenueQoQ": -2.35,
      "grossProfit": 84168778.45,
      "netProfit": 29116067.23,
      "netProfitYoY": 64.2,
      "netProfitQoQ": 5.56,
      "deductNetProfit": 20635490.24,
      "deductNetProfitYoY": 768.37,
      "deductNetProfitQoQ": 12.38,
      "nonRecurringPnL": 8480576.99,
      "nonRecurringRatio": 29.13,
      "weightedROE": 3.51,
      "deductROE": null,
      "grossMargin": 24.97,
      "netMargin": 11.69,
      "cashToRevenue": -0.1,
      "cashToProfit": 0.29,
      "debtRatio": 74.81,
      "currentRatio": 1.304994845778,
      "quickRatio": 0.847330226263,
      "assetTurnover": 0.091488292031,
      "inventoryTurnoverDays": 410.25461810902,
      "receivableTurnoverDays": 152.300674486432
    },
    {
      "reportDate": "2023-12-31",
      "reportName": "2023年报",
      "reportType": "年报",
      "basicEPS": 0.99,
      "dilutedEPS": 0.99,
      "deductEPS": 0.71,
      "bps": 3.914488594567,
      "opsCashPerShare": 0.020594276875,
      "totalRevenue": 2237235267.21,
      "totalRevenueYoY": 2.18,
      "totalRevenueQoQ": -0.55,
      "grossProfit": 541232413.62,
      "netProfit": 204781020.16,
      "netProfitYoY": 92.38,
      "netProfitQoQ": 96.97,
      "deductNetProfit": 147541124.58,
      "deductNetProfitYoY": 67.09,
      "deductNetProfitQoQ": 96.28,
      "nonRecurringPnL": 57239895.58,
      "nonRecurringRatio": 27.95,
      "weightedROE": 21.29,
      "deductROE": 15.34,
      "grossMargin": 24.19,
      "netMargin": 12.46,
      "cashToRevenue": 0.0,
      "cashToProfit": 0.12,
      "debtRatio": 73.69,
      "currentRatio": 1.321895904625,
      "quickRatio": 0.820275189033,
      "assetTurnover": 0.611478592922,
      "inventoryTurnoverDays": 230.394752305731,
      "receivableTurnoverDays": 89.319408042583
    },
    {
      "reportDate": "2023-09-30",
      "reportName": "2023三季报",
      "reportType": "三季报",
      "basicEPS": 0.2929,
      "dilutedEPS": 0.2929,
      "deductEPS": null,
      "bps": 3.239158941731,
      "opsCashPerShare": -0.815727099231,
      "totalRevenue": 1519939154.95,
      "totalRevenueYoY": 4.11,
      "totalRevenueQoQ": -11.25,
      "grossProfit": 332109419.36,
      "netProfit": 60740474.13,
      "netProfitYoY": -3.93,
      "netProfitQoQ": -27.11,
      "deductNetProfit": 47595881.8,
      "deductNetProfitYoY": -21.63,
      "deductNetProfitQoQ": -33.53,
      "nonRecurringPnL": 13144592.33,
      "nonRecurringRatio": 21.64,
      "weightedROE": 6.24,
      "deductROE": null,
      "grossMargin": 21.85,
      "netMargin": 7.42,
      "cashToRevenue": -0.11,
      "cashToProfit": 0.09,
      "debtRatio": 81.25,
      "currentRatio": 1.172506699475,
      "quickRatio": 0.642985070836,
      "assetTurnover": 0.385223142122,
      "inventoryTurnoverDays": 296.074798801396,
      "receivableTurnoverDays": 104.14687612037
    },
    {
      "reportDate": "2023-06-30",
      "reportName": "2023中报",
      "reportType": "中报",
      "basicEPS": 0.2379,
      "dilutedEPS": 0.2379,
      "deductEPS": 0.1744,
      "bps": 4.789834966971,
      "opsCashPerShare": -1.078445297019,
      "totalRevenue": 1058468017.09,
      "totalRevenueYoY": 48.42,
      "totalRevenueQoQ": 10.82,
      "grossProfit": 239008936.34,
      "netProfit": 49482040.69,
      "netProfitYoY": 272.24,
      "netProfitQoQ": -1.67,
      "deductNetProfit": 36280702.89,
      "deductNetProfitYoY": 215.64,
      "deductNetProfitQoQ": 1.07,
      "nonRecurringPnL": 13201337.8,
      "nonRecurringRatio": 26.68,
      "weightedROE": 4.84,
      "deductROE": 3.55,
      "grossMargin": 22.58,
      "netMargin": 9.46,
      "cashToRevenue": -0.21,
      "cashToProfit": -0.09,
      "debtRatio": 71.26,
      "currentRatio": 1.25487692213,
      "quickRatio": 0.734393964709,
      "assetTurnover": 0.266622591853,
      "inventoryTurnoverDays": 273.579867876207,
      "receivableTurnoverDays": 107.967532884245
    },
    {
      "reportDate": "2023-03-31",
      "reportName": "2023一季报",
      "reportType": "一季报",
      "basicEPS": 0.0853,
      "dilutedEPS": 0.0853,
      "deductEPS": null,
      "bps": 4.877563977212,
      "opsCashPerShare": -1.275960383606,
      "totalRevenue": 389543210.76,
      "totalRevenueYoY": 33.5,
      "totalRevenueQoQ": 4.46,
      "grossProfit": 80641551.41,
      "netProfit": 17732260.85,
      "netProfitYoY": 184.93,
      "netProfitQoQ": 36.27,
      "deductNetProfit": 2376352.58,
      "deductNetProfitYoY": 111.2,
      "deductNetProfitQoQ": 26.72,
      "nonRecurringPnL": 15355908.27,
      "nonRecurringRatio": 86.6,
      "weightedROE": 1.76,
      "deductROE": null,
      "grossMargin": 20.7,
      "netMargin": 8.83,
      "cashToRevenue": -0.68,
      "cashToProfit": -0.48,
      "debtRatio": 69.05,
      "currentRatio": 1.293083337519,
      "quickRatio": 0.811184894421,
      "assetTurnover": 0.101011135833,
      "inventoryTurnoverDays": 330.150502257521,
      "receivableTurnoverDays": 142.738099156701
    },
    {
      "reportDate": "2022-12-31",
      "reportName": "2022年报",
      "reportType": "年报",
      "basicEPS": 0.51,
      "dilutedEPS": 0.51,
      "deductEPS": 0.42,
      "bps": 4.792312723125,
      "opsCashPerShare": 0.305032469856,
      "totalRevenue": 2189552898.02,
      "totalRevenueYoY": 86.39,
      "totalRevenueQoQ": 16.31,
      "grossProfit": 460904451.91,
      "netProfit": 106446884.7,
      "netProfitYoY": 398.99,
      "netProfitQoQ": 36.1,
      "deductNetProfit": 88302254.19,
      "deductNetProfitYoY": 257.59,
      "deductNetProfitQoQ": 39.96,
      "nonRecurringPnL": 18144630.51,
      "nonRecurringRatio": 17.05,
      "weightedROE": 11.46,
      "deductROE": 9.5,
      "grossMargin": 21.05,
      "netMargin": 7.67,
      "cashToRevenue": 0.03,
      "cashToProfit": 0.27,
      "debtRatio": 67.32,
      "currentRatio": 1.313971576812,
      "quickRatio": 0.884115789922,
      "assetTurnover": 0.797326580021,
      "inventoryTurnoverDays": 150.442496197761,
      "receivableTurnoverDays": 92.301498852553
    },
    {
      "reportDate": "2022-09-30",
      "reportName": "2022三季报",
      "reportType": "三季报",
      "basicEPS": 0.304,
      "dilutedEPS": 0.304,
      "deductEPS": null,
      "bps": 4.515536952115,
      "opsCashPerShare": 0.22911383351,
      "totalRevenue": 1459916121.64,
      "totalRevenueYoY": 94.12,
      "totalRevenueQoQ": 33.06,
      "grossProfit": 264072702.07,
      "netProfit": 63222951.17,
      "netProfitYoY": 224.96,
      "netProfitQoQ": 342.99,
      "deductNetProfit": 60730296.2,
      "deductNetProfitYoY": 204.0,
      "deductNetProfitQoQ": 8784.35,
      "nonRecurringPnL": 2492654.97,
      "nonRecurringRatio": 3.94,
      "weightedROE": 6.99,
      "deductROE": null,
      "grossMargin": 18.09,
      "netMargin": 6.05,
      "cashToRevenue": 0.03,
      "cashToProfit": 0.15,
      "debtRatio": 70.82,
      "currentRatio": 1.264517411343,
      "quickRatio": 0.794569680365,
      "assetTurnover": 0.527030307391,
      "inventoryTurnoverDays": 185.795140744968,
      "receivableTurnoverDays": 109.857216862261
    },
    {
      "reportDate": "2022-06-30",
      "reportName": "2022中报",
      "reportType": "中报",
      "basicEPS": 0.0639,
      "dilutedEPS": 0.0639,
      "deductEPS": 0.0553,
      "bps": 4.255079493606,
      "opsCashPerShare": -0.945682675962,
      "totalRevenue": 713178054.51,
      "totalRevenueYoY": 50.75,
      "totalRevenueQoQ": 9.4,
      "grossProfit": 100678937.21,
      "netProfit": 13293026.87,
      "netProfitYoY": 133.26,
      "netProfitQoQ": 161.12,
      "deductNetProfit": 11494173.52,
      "deductNetProfitYoY": 125.4,
      "deductNetProfitQoQ": 101.49,
      "nonRecurringPnL": 1798853.35,
      "nonRecurringRatio": 13.53,
      "weightedROE": 1.52,
      "deductROE": 1.31,
      "grossMargin": 14.12,
      "netMargin": 1.7,
      "cashToRevenue": -0.28,
      "cashToProfit": 0.01,
      "debtRatio": 69.57,
      "currentRatio": 1.132370480608,
      "quickRatio": 0.687498498743,
      "assetTurnover": 0.278453344141,
      "inventoryTurnoverDays": 216.64609079023,
      "receivableTurnoverDays": 134.653928533461
    },
    {
      "reportDate": "2022-03-31",
      "reportName": "2022一季报",
      "reportType": "一季报",
      "basicEPS": -0.1004,
      "dilutedEPS": -0.1004,
      "deductEPS": null,
      "bps": 4.070775007692,
      "opsCashPerShare": -0.498043436202,
      "totalRevenue": 291795109.3,
      "totalRevenueYoY": 68.41,
      "totalRevenueQoQ": 10.09,
      "grossProfit": 35840619.43,
      "netProfit": -20878730.35,
      "netProfitYoY": 24.34,
      "netProfitQoQ": 18.86,
      "deductNetProfit": -21214565.19,
      "deductNetProfitYoY": 28.0,
      "deductNetProfitQoQ": 14.72,
      "nonRecurringPnL": 335834.84,
      "nonRecurringRatio": -1.61,
      "weightedROE": -2.43,
      "deductROE": null,
      "grossMargin": 12.28,
      "netMargin": -7.29,
      "cashToRevenue": -0.36,
      "cashToProfit": 0.14,
      "debtRatio": 55.48,
      "currentRatio": 1.507449263425,
      "quickRatio": 1.010227504366,
      "assetTurnover": 0.156442100855,
      "inventoryTurnoverDays": 165.410311139442,
      "receivableTurnoverDays": 148.890177121185
    },
    {
      "reportDate": "2021-12-31",
      "reportName": "2021年报",
      "reportType": "年报",
      "basicEPS": -0.17,
      "dilutedEPS": -0.17,
      "deductEPS": -0.27,
      "bps": 4.176162220144,
      "opsCashPerShare": -0.590090817404,
      "totalRevenue": 1174734809.76,
      "totalRevenueYoY": 38.58,
      "totalRevenueQoQ": 14.06,
      "grossProfit": 143246586.21,
      "netProfit": -35601723.73,
      "netProfitYoY": -920.15,
      "netProfitQoQ": -13.97,
      "deductNetProfit": -56033732.98,
      "deductNetProfitYoY": -363.26,
      "deductNetProfitQoQ": -32.84,
      "nonRecurringPnL": 20432009.25,
      "nonRecurringRatio": -57.39,
      "weightedROE": -4.01,
      "deductROE": -6.31,
      "grossMargin": 12.19,
      "netMargin": -3.18,
      "cashToRevenue": -0.1,
      "cashToProfit": 0.1,
      "debtRatio": 50.77,
      "currentRatio": 1.634342075592,
      "quickRatio": 1.13364993756,
      "assetTurnover": 0.696517760392,
      "inventoryTurnoverDays": 139.678968624895,
      "receivableTurnoverDays": 122.21754314453
    },
    {
      "reportDate": "2021-09-30",
      "reportName": "2021三季报",
      "reportType": "三季报",
      "basicEPS": -0.2432,
      "dilutedEPS": -0.2432,
      "deductEPS": null,
      "bps": 4.113168653942,
      "opsCashPerShare": -0.577320586298,
      "totalRevenue": 752062488.53,
      "totalRevenueYoY": 31.99,
      "totalRevenueQoQ": 7.02,
      "grossProfit": 82611251.55,
      "netProfit": -50593896.53,
      "netProfitYoY": -236.93,
      "netProfitQoQ": 13.54,
      "deductNetProfit": -58393236.65,
      "deductNetProfitYoY": -106.29,
      "deductNetProfitQoQ": 14.6,
      "nonRecurringPnL": 7799340.12,
      "nonRecurringRatio": -15.42,
      "weightedROE": -5.74,
      "deductROE": null,
      "grossMargin": 10.98,
      "netMargin": -6.87,
      "cashToRevenue": -0.16,
      "cashToProfit": 0.07,
      "debtRatio": 54.38,
      "currentRatio": 1.479847571579,
      "quickRatio": 0.975410233061,
      "assetTurnover": 0.430771941325,
      "inventoryTurnoverDays": 175.420682940059,
      "receivableTurnoverDays": 120.559488183631
    },
    {
      "reportDate": "2021-06-30",
      "reportName": "2021中报",
      "reportType": "中报",
      "basicEPS": -0.1921,
      "dilutedEPS": -0.1921,
      "deductEPS": -0.2175,
      "bps": 4.160419459519,
      "opsCashPerShare": -0.453775637404,
      "totalRevenue": 473088063.23,
      "totalRevenueYoY": 32.01,
      "totalRevenueQoQ": 3.49,
      "grossProfit": 50303633.05,
      "netProfit": -39964800.06,
      "netProfitYoY": -8046.95,
      "netProfitQoQ": -48.08,
      "deductNetProfit": -45249682.31,
      "deductNetProfitYoY": -469.09,
      "deductNetProfitQoQ": -24.44,
      "nonRecurringPnL": 5284882.25,
      "nonRecurringRatio": -13.22,
      "weightedROE": -4.5,
      "deductROE": -5.1,
      "grossMargin": 10.63,
      "netMargin": -8.41,
      "cashToRevenue": -0.2,
      "cashToProfit": 0.04,
      "debtRatio": 51.87,
      "currentRatio": 1.541988945456,
      "quickRatio": 1.031157464198,
      "assetTurnover": 0.277086764231,
      "inventoryTurnoverDays": 176.365018657319,
      "receivableTurnoverDays": 120.424110341178
    }
  ],
  "income": [
    {
      "reportDate": "2026-03-31",
      "reportName": "2026一季报",
      "operateIncome": 117862064.14,
      "operateIncomeYoY": -12.78,
      "revenue": 117862064.14,
      "revenueYoY": -12.78,
      "operateCost": 120096511.14,
      "operateCostYoY": 1.14,
      "grossProfit": -2234447.0,
      "grossMargin": -1.9,
      "totalProfit": -19736907.0,
      "netProfit": -19705874.08,
      "parentNetProfit": null,
      "parentNetProfitYoY": null,
      "saleExpense": 3065320.67,
      "saleExpenseRatio": 2.6,
      "manageExpense": 19523824.76,
      "manageExpenseRatio": 16.56,
      "researchExpense": 7420051.32,
      "researchRatio": 6.3,
      "financeExpense": 5320303.52,
      "financeExpenseRatio": 4.51,
      "netMargin": null
    },
    {
      "reportDate": "2025-12-31",
      "reportName": "2025年报",
      "operateIncome": 1078772647.45,
      "operateIncomeYoY": -21.46,
      "revenue": 1078772647.45,
      "revenueYoY": -21.46,
      "operateCost": 837774614.1,
      "operateCostYoY": -19.98,
      "grossProfit": 240998033.35,
      "grossMargin": 22.34,
      "totalProfit": 28774058.91,
      "netProfit": 15745355.36,
      "parentNetProfit": null,
      "parentNetProfitYoY": null,
      "saleExpense": 11374558.52,
      "saleExpenseRatio": 1.05,
      "manageExpense": 75369718.36,
      "manageExpenseRatio": 6.99,
      "researchExpense": 66308721.24,
      "researchRatio": 6.15,
      "financeExpense": 25806689.83,
      "financeExpenseRatio": 2.39,
      "netMargin": null
    },
    {
      "reportDate": "2025-09-30",
      "reportName": "2025三季报",
      "operateIncome": 880995160.78,
      "operateIncomeYoY": -16.99,
      "revenue": 880995160.78,
      "revenueYoY": -16.99,
      "operateCost": 659214871.94,
      "operateCostYoY": -20.09,
      "grossProfit": 221780288.84,
      "grossMargin": 25.17,
      "totalProfit": 92198462.29,
      "netProfit": 75724035.24,
      "parentNetProfit": null,
      "parentNetProfitYoY": null,
      "saleExpense": 8680205.53,
      "saleExpenseRatio": 0.99,
      "manageExpense": 55866310.04,
      "manageExpenseRatio": 6.34,
      "researchExpense": 48496349.19,
      "researchRatio": 5.5,
      "financeExpense": 18961691.05,
      "financeExpenseRatio": 2.15,
      "netMargin": null
    },
    {
      "reportDate": "2025-06-30",
      "reportName": "2025中报",
      "operateIncome": 386344628.65,
      "operateIncomeYoY": -43.4,
      "revenue": 386344628.65,
      "revenueYoY": -43.4,
      "operateCost": 326170910.36,
      "operateCostYoY": -37.4,
      "grossProfit": 60173718.29,
      "grossMargin": 15.58,
      "totalProfit": -46807415.69,
      "netProfit": -43078593.3,
      "parentNetProfit": null,
      "parentNetProfitYoY": null,
      "saleExpense": 5943788.71,
      "saleExpenseRatio": 1.54,
      "manageExpense": 36821674.02,
      "manageExpenseRatio": 9.53,
      "researchExpense": 40588955.75,
      "researchRatio": 10.51,
      "financeExpense": 13797561.29,
      "financeExpenseRatio": 3.57,
      "netMargin": null
    },
    {
      "reportDate": "2025-03-31",
      "reportName": "2025一季报",
      "operateIncome": 135126133.69,
      "operateIncomeYoY": -59.91,
      "revenue": 135126133.69,
      "revenueYoY": -59.91,
      "operateCost": 118743540.77,
      "operateCostYoY": -53.04,
      "grossProfit": 16382592.92,
      "grossMargin": 12.12,
      "totalProfit": -30305779.76,
      "netProfit": -31509470.73,
      "parentNetProfit": null,
      "parentNetProfitYoY": null,
      "saleExpense": 2791117.59,
      "saleExpenseRatio": 2.07,
      "manageExpense": 17157611.48,
      "manageExpenseRatio": 12.7,
      "researchExpense": 15976575.14,
      "researchRatio": 11.82,
      "financeExpense": 6851469.66,
      "financeExpenseRatio": 5.07,
      "netMargin": null
    },
    {
      "reportDate": "2024-12-31",
      "reportName": "2024年报",
      "operateIncome": 1373603914.21,
      "operateIncomeYoY": -38.6,
      "revenue": 1373603914.21,
      "revenueYoY": -38.6,
      "operateCost": 1046929045.35,
      "operateCostYoY": -38.27,
      "grossProfit": 326674868.86,
      "grossMargin": 23.78,
      "totalProfit": 169257223.48,
      "netProfit": 142073643.36,
      "parentNetProfit": null,
      "parentNetProfitYoY": null,
      "saleExpense": 16084921.34,
      "saleExpenseRatio": 1.17,
      "manageExpense": 76931125.65,
      "manageExpenseRatio": 5.6,
      "researchExpense": 56053649.64,
      "researchRatio": 4.08,
      "financeExpense": 20447275.53,
      "financeExpenseRatio": 1.49,
      "netMargin": null
    },
    {
      "reportDate": "2024-09-30",
      "reportName": "2024三季报",
      "operateIncome": 1061265800.13,
      "operateIncomeYoY": -30.18,
      "revenue": 1061265800.13,
      "revenueYoY": -30.18,
      "operateCost": 824954725.18,
      "operateCostYoY": -30.55,
      "grossProfit": 236311074.95,
      "grossMargin": 22.27,
      "totalProfit": 117341523.88,
      "netProfit": 107341416.12,
      "parentNetProfit": null,
      "parentNetProfitYoY": null,
      "saleExpense": 12814993.01,
      "saleExpenseRatio": 1.21,
      "manageExpense": 57822806.79,
      "manageExpenseRatio": 5.45,
      "researchExpense": 36233397.8,
      "researchRatio": 3.41,
      "financeExpense": 16239383.62,
      "financeExpenseRatio": 1.53,
      "netMargin": null
    },
    {
      "reportDate": "2024-06-30",
      "reportName": "2024中报",
      "operateIncome": 682622587.89,
      "operateIncomeYoY": -35.51,
      "revenue": 682622587.89,
      "revenueYoY": -35.51,
      "operateCost": 521003642.98,
      "operateCostYoY": -36.42,
      "grossProfit": 161618944.91,
      "grossMargin": 23.68,
      "totalProfit": 86882813.58,
      "netProfit": 76222942.52,
      "parentNetProfit": null,
      "parentNetProfitYoY": null,
      "saleExpense": 8588361.15,
      "saleExpenseRatio": 1.26,
      "manageExpense": 39449098.61,
      "manageExpenseRatio": 5.78,
      "researchExpense": 18200187.27,
      "researchRatio": 2.67,
      "financeExpense": 9942821.49,
      "financeExpenseRatio": 1.46,
      "netMargin": null
    },
    {
      "reportDate": "2024-03-31",
      "reportName": "2024一季报",
      "operateIncome": 337052539.27,
      "operateIncomeYoY": -13.47,
      "revenue": 337052539.27,
      "revenueYoY": -13.47,
      "operateCost": 252883760.82,
      "operateCostYoY": -18.13,
      "grossProfit": 84168778.45,
      "grossMargin": 24.97,
      "totalProfit": 49310493.91,
      "netProfit": 39387532.34,
      "parentNetProfit": null,
      "parentNetProfitYoY": null,
      "saleExpense": 6985004.39,
      "saleExpenseRatio": 2.07,
      "manageExpense": 19139699.54,
      "manageExpenseRatio": 5.68,
      "researchExpense": 6450880.56,
      "researchRatio": 1.91,
      "financeExpense": 5865158.29,
      "financeExpenseRatio": 1.74,
      "netMargin": null
    },
    {
      "reportDate": "2023-12-31",
      "reportName": "2023年报",
      "operateIncome": 2237235267.21,
      "operateIncomeYoY": 2.18,
      "revenue": 2237235267.21,
      "revenueYoY": 2.18,
      "operateCost": 1696002853.59,
      "operateCostYoY": -1.89,
      "grossProfit": 541232413.62,
      "grossMargin": 24.19,
      "totalProfit": 337475827.12,
      "netProfit": 278798829.65,
      "parentNetProfit": null,
      "parentNetProfitYoY": null,
      "saleExpense": 65670996.45,
      "saleExpenseRatio": 2.94,
      "manageExpense": 91498206.93,
      "manageExpenseRatio": 4.09,
      "researchExpense": 80682985.84,
      "researchRatio": 3.61,
      "financeExpense": 7113641.81,
      "financeExpenseRatio": 0.32,
      "netMargin": null
    },
    {
      "reportDate": "2023-09-30",
      "reportName": "2023三季报",
      "operateIncome": 1519939154.95,
      "operateIncomeYoY": 4.11,
      "revenue": 1519939154.95,
      "revenueYoY": 4.11,
      "operateCost": 1187829735.59,
      "operateCostYoY": -0.67,
      "grossProfit": 332109419.36,
      "grossMargin": 21.85,
      "totalProfit": 137915890.78,
      "netProfit": 112729615.91,
      "parentNetProfit": null,
      "parentNetProfitYoY": null,
      "saleExpense": 58169294.81,
      "saleExpenseRatio": 3.83,
      "manageExpense": 63945359.1,
      "manageExpenseRatio": 4.21,
      "researchExpense": 67829163.29,
      "researchRatio": 4.46,
      "financeExpense": 6515501.65,
      "financeExpenseRatio": 0.43,
      "netMargin": null
    },
    {
      "reportDate": "2023-06-30",
      "reportName": "2023中报",
      "operateIncome": 1058468017.09,
      "operateIncomeYoY": 48.42,
      "revenue": 1058468017.09,
      "revenueYoY": 48.42,
      "operateCost": 819459080.75,
      "operateCostYoY": 33.79,
      "grossProfit": 239008936.34,
      "grossMargin": 22.58,
      "totalProfit": 117802541.96,
      "netProfit": 100178863.79,
      "parentNetProfit": null,
      "parentNetProfitYoY": null,
      "saleExpense": 34496238.81,
      "saleExpenseRatio": 3.26,
      "manageExpense": 42319923.11,
      "manageExpenseRatio": 4.0,
      "researchExpense": 46115785.2,
      "researchRatio": 4.36,
      "financeExpense": 1426914.57,
      "financeExpenseRatio": 0.13,
      "netMargin": null
    },
    {
      "reportDate": "2023-03-31",
      "reportName": "2023一季报",
      "operateIncome": 389543210.76,
      "operateIncomeYoY": 33.5,
      "revenue": 389543210.76,
      "revenueYoY": 33.5,
      "operateCost": 308901659.35,
      "operateCostYoY": 20.69,
      "grossProfit": 80641551.41,
      "grossMargin": 20.7,
      "totalProfit": 42204151.99,
      "netProfit": 34400379.14,
      "parentNetProfit": null,
      "parentNetProfitYoY": null,
      "saleExpense": 14246158.11,
      "saleExpenseRatio": 3.66,
      "manageExpense": 20782049.05,
      "manageExpenseRatio": 5.33,
      "researchExpense": 15161500.83,
      "researchRatio": 3.89,
      "financeExpense": 6760611.2,
      "financeExpenseRatio": 1.74,
      "netMargin": null
    },
    {
      "reportDate": "2022-12-31",
      "reportName": "2022年报",
      "operateIncome": 2189552898.02,
      "operateIncomeYoY": 86.39,
      "revenue": 2189552898.02,
      "revenueYoY": 86.39,
      "operateCost": 1728648446.11,
      "operateCostYoY": 67.59,
      "grossProfit": 460904451.91,
      "grossMargin": 21.05,
      "totalProfit": 199506597.04,
      "netProfit": 167885776.34,
      "parentNetProfit": null,
      "parentNetProfitYoY": null,
      "saleExpense": 78412904.82,
      "saleExpenseRatio": 3.58,
      "manageExpense": 78017594.78,
      "manageExpenseRatio": 3.56,
      "researchExpense": 62233778.64,
      "researchRatio": 2.84,
      "financeExpense": -3091063.38,
      "financeExpenseRatio": -0.14,
      "netMargin": null
    },
    {
      "reportDate": "2022-09-30",
      "reportName": "2022三季报",
      "operateIncome": 1459916121.64,
      "operateIncomeYoY": 94.12,
      "revenue": 1459916121.64,
      "revenueYoY": 94.12,
      "operateCost": 1195843419.57,
      "operateCostYoY": 78.63,
      "grossProfit": 264072702.07,
      "grossMargin": 18.09,
      "totalProfit": 101197211.11,
      "netProfit": 88256462.03,
      "parentNetProfit": null,
      "parentNetProfitYoY": null,
      "saleExpense": 51623958.6,
      "saleExpenseRatio": 3.54,
      "manageExpense": 56737132.13,
      "manageExpenseRatio": 3.89,
      "researchExpense": 36867088.62,
      "researchRatio": 2.53,
      "financeExpense": -14106054.79,
      "financeExpenseRatio": -0.97,
      "netMargin": null
    },
    {
      "reportDate": "2022-06-30",
      "reportName": "2022中报",
      "operateIncome": 713178054.51,
      "operateIncomeYoY": 50.75,
      "revenue": 713178054.51,
      "revenueYoY": 50.75,
      "operateCost": 612499117.3,
      "operateCostYoY": 44.87,
      "grossProfit": 100678937.21,
      "grossMargin": 14.12,
      "totalProfit": 15125092.66,
      "netProfit": 12110092.56,
      "parentNetProfit": null,
      "parentNetProfitYoY": null,
      "saleExpense": 34441694.87,
      "saleExpenseRatio": 4.83,
      "manageExpense": 28714486.77,
      "manageExpenseRatio": 4.03,
      "researchExpense": 16734178.94,
      "researchRatio": 2.35,
      "financeExpense": -11579346.64,
      "financeExpenseRatio": -1.62,
      "netMargin": null
    },
    {
      "reportDate": "2022-03-31",
      "reportName": "2022一季报",
      "operateIncome": 291795109.3,
      "operateIncomeYoY": 68.41,
      "revenue": 291795109.3,
      "revenueYoY": 68.41,
      "operateCost": 255954489.87,
      "operateCostYoY": 67.48,
      "grossProfit": 35840619.43,
      "grossMargin": 12.28,
      "totalProfit": -18272584.79,
      "netProfit": -21279570.92,
      "parentNetProfit": null,
      "parentNetProfitYoY": null,
      "saleExpense": 19956848.83,
      "saleExpenseRatio": 6.84,
      "manageExpense": 15606854.48,
      "manageExpenseRatio": 5.35,
      "researchExpense": 6629531.02,
      "researchRatio": 2.27,
      "financeExpense": 3756500.32,
      "financeExpenseRatio": 1.29,
      "netMargin": null
    },
    {
      "reportDate": "2021-12-31",
      "reportName": "2021年报",
      "operateIncome": 1174734809.76,
      "operateIncomeYoY": 38.58,
      "revenue": 1174734809.76,
      "revenueYoY": 38.58,
      "operateCost": 1031488223.55,
      "operateCostYoY": 46.73,
      "grossProfit": 143246586.21,
      "grossMargin": 12.19,
      "totalProfit": -41089147.99,
      "netProfit": -37325219.19,
      "parentNetProfit": null,
      "parentNetProfitYoY": null,
      "saleExpense": 56345450.13,
      "saleExpenseRatio": 4.8,
      "manageExpense": 57926470.41,
      "manageExpenseRatio": 4.93,
      "researchExpense": 36379351.91,
      "researchRatio": 3.1,
      "financeExpense": 18799682.73,
      "financeExpenseRatio": 1.6,
      "netMargin": null
    },
    {
      "reportDate": "2021-09-30",
      "reportName": "2021三季报",
      "operateIncome": 752062488.53,
      "operateIncomeYoY": 31.99,
      "revenue": 752062488.53,
      "revenueYoY": 31.99,
      "operateCost": 669451236.98,
      "operateCostYoY": 44.6,
      "grossProfit": 82611251.55,
      "grossMargin": 10.98,
      "totalProfit": -48175167.86,
      "netProfit": -51641778.23,
      "parentNetProfit": null,
      "parentNetProfitYoY": null,
      "saleExpense": 34525581.69,
      "saleExpenseRatio": 4.59,
      "manageExpense": 42766753.99,
      "manageExpenseRatio": 5.69,
      "researchExpense": 26550940.56,
      "researchRatio": 3.53,
      "financeExpense": 12644788.62,
      "financeExpenseRatio": 1.68,
      "netMargin": null
    },
    {
      "reportDate": "2021-06-30",
      "reportName": "2021中报",
      "operateIncome": 473088063.23,
      "operateIncomeYoY": 32.01,
      "revenue": 473088063.23,
      "revenueYoY": 32.01,
      "operateCost": 422784430.18,
      "operateCostYoY": 47.95,
      "grossProfit": 50303633.05,
      "grossMargin": 10.63,
      "totalProfit": -37443005.87,
      "netProfit": -39782655.51,
      "parentNetProfit": null,
      "parentNetProfitYoY": null,
      "saleExpense": 22177390.11,
      "saleExpenseRatio": 4.69,
      "manageExpense": 28222118.66,
      "manageExpenseRatio": 5.97,
      "researchExpense": 18540211.43,
      "researchRatio": 3.92,
      "financeExpense": 9595535.32,
      "financeExpenseRatio": 2.03,
      "netMargin": null
    }
  ],
  "balance": [
    {
      "reportDate": "2026-03-31",
      "reportName": "2026一季报",
      "totalAssets": 2491304270.64,
      "totalAssetsYoY": -19.96,
      "currentAssets": 1574688052.65,
      "nonCurrentAssets": 916616217.99,
      "monetaryFunds": 219725583.11,
      "accountsReceivable": 435164752.65,
      "inventory": 599811083.89,
      "fixedAsset": 363569824.97,
      "intangibleAsset": 61994586.48,
      "goodwill": 308369819.24,
      "totalLiabilities": 1558770518.44,
      "totalLiabilitiesYoY": -28.62,
      "currentLiabilities": 1307549102.54,
      "nonCurrentLiabilities": 251221415.9,
      "shortLoan": 263413879.51,
      "longLoan": 207806816.66,
      "bondsPayable": null,
      "totalEquity": 932533752.2,
      "totalEquityYoY": 0.42,
      "parentEquity": 790989752.86,
      "minorityEquity": 141543999.34,
      "debtRatio": 62.57,
      "currentRatio": 1.2,
      "equityMultiplier": 2.67
    },
    {
      "reportDate": "2025-12-31",
      "reportName": "2025年报",
      "totalAssets": 2488400068.44,
      "totalAssetsYoY": -14.83,
      "currentAssets": 1558686059.2,
      "nonCurrentAssets": 929714009.24,
      "monetaryFunds": 261181353.6,
      "accountsReceivable": 513010712.25,
      "inventory": 540822518.2,
      "fixedAsset": 367463444.79,
      "intangibleAsset": 63241556.31,
      "goodwill": 308369819.24,
      "totalLiabilities": 1533016331.37,
      "totalLiabilitiesYoY": -21.42,
      "currentLiabilities": 1270749297.94,
      "nonCurrentLiabilities": 262267033.43,
      "shortLoan": 308503419.79,
      "longLoan": 227813691.66,
      "bondsPayable": null,
      "totalEquity": 955383737.07,
      "totalEquityYoY": -1.57,
      "parentEquity": 810655822.2,
      "minorityEquity": 144727914.87,
      "debtRatio": 61.61,
      "currentRatio": 1.23,
      "equityMultiplier": 2.6
    },
    {
      "reportDate": "2025-09-30",
      "reportName": "2025三季报",
      "totalAssets": 2734700337.72,
      "totalAssetsYoY": -17.04,
      "currentAssets": 1878963404.61,
      "nonCurrentAssets": 855736933.11,
      "monetaryFunds": 342322923.68,
      "accountsReceivable": 560602612.47,
      "inventory": 591125183.94,
      "fixedAsset": 375372887.13,
      "intangibleAsset": 64488526.17,
      "goodwill": 308369819.24,
      "totalLiabilities": 1717049872.54,
      "totalLiabilitiesYoY": -27.6,
      "currentLiabilities": 1354206461.67,
      "nonCurrentLiabilities": 362843410.87,
      "shortLoan": 338588737.2,
      "longLoan": 324795346.67,
      "bondsPayable": null,
      "totalEquity": 1017650465.18,
      "totalEquityYoY": 10.07,
      "parentEquity": 861720008.54,
      "minorityEquity": 155930456.64,
      "debtRatio": 62.79,
      "currentRatio": 1.39,
      "equityMultiplier": 2.69
    },
    {
      "reportDate": "2025-06-30",
      "reportName": "2025中报",
      "totalAssets": 2909942635.45,
      "totalAssetsYoY": -20.56,
      "currentAssets": 2043934216.24,
      "nonCurrentAssets": 866008419.21,
      "monetaryFunds": 442517782.81,
      "accountsReceivable": 570576105.36,
      "inventory": 738634599.06,
      "fixedAsset": 383441242.79,
      "intangibleAsset": 65746631.6,
      "goodwill": 308369819.24,
      "totalLiabilities": 2012814472.7,
      "totalLiabilitiesYoY": -26.53,
      "currentLiabilities": 1603400970.85,
      "nonCurrentLiabilities": 409413501.85,
      "shortLoan": 343019972.62,
      "longLoan": 366934156.38,
      "bondsPayable": null,
      "totalEquity": 897128162.75,
      "totalEquityYoY": -2.85,
      "parentEquity": 763328300.65,
      "minorityEquity": 133799862.1,
      "debtRatio": 69.17,
      "currentRatio": 1.27,
      "equityMultiplier": 3.24
    },
    {
      "reportDate": "2025-03-31",
      "reportName": "2025一季报",
      "totalAssets": 3112386534.68,
      "totalAssetsYoY": -16.95,
      "currentAssets": 2241381451.56,
      "nonCurrentAssets": 871005083.12,
      "monetaryFunds": 437935679.63,
      "accountsReceivable": 636722658.99,
      "inventory": 757056668.18,
      "fixedAsset": 391970591.99,
      "intangibleAsset": 66735179.47,
      "goodwill": 308369819.24,
      "totalLiabilities": 2183763095.52,
      "totalLiabilitiesYoY": -22.11,
      "currentLiabilities": 1727458501.8,
      "nonCurrentLiabilities": 456304593.72,
      "shortLoan": 389092941.55,
      "longLoan": 440949838.22,
      "bondsPayable": null,
      "totalEquity": 928623439.16,
      "totalEquityYoY": -1.65,
      "parentEquity": 793583586.29,
      "minorityEquity": 135039852.87,
      "debtRatio": 70.16,
      "currentRatio": 1.3,
      "equityMultiplier": 3.35
    },
    {
      "reportDate": "2024-12-31",
      "reportName": "2024年报",
      "totalAssets": 2921611067.7,
      "totalAssetsYoY": -19.3,
      "currentAssets": 2060627682.3,
      "nonCurrentAssets": 860983385.4,
      "monetaryFunds": 501906490.15,
      "accountsReceivable": 555686883.2,
      "inventory": 748576385.1,
      "fixedAsset": 399194173.04,
      "intangibleAsset": 67979806.96,
      "goodwill": 308369819.24,
      "totalLiabilities": 1950991132.04,
      "totalLiabilitiesYoY": -26.88,
      "currentLiabilities": 1505426182.72,
      "nonCurrentLiabilities": 445564949.32,
      "shortLoan": 300016433.8,
      "longLoan": 391007254.87,
      "bondsPayable": null,
      "totalEquity": 970619935.66,
      "totalEquityYoY": 1.91,
      "parentEquity": 817992535.93,
      "minorityEquity": 152627399.73,
      "debtRatio": 66.78,
      "currentRatio": 1.37,
      "equityMultiplier": 3.01
    },
    {
      "reportDate": "2024-09-30",
      "reportName": "2024三季报",
      "totalAssets": 3296231291.26,
      "totalAssetsYoY": -21.41,
      "currentAssets": 2452350608.23,
      "nonCurrentAssets": 843880683.03,
      "monetaryFunds": 468771104.98,
      "accountsReceivable": 690803900.88,
      "inventory": 842576129.33,
      "fixedAsset": 402692114.69,
      "intangibleAsset": 56220040.04,
      "goodwill": 308369819.24,
      "totalLiabilities": 2371650066.22,
      "totalLiabilitiesYoY": -30.41,
      "currentLiabilities": 1882924525.65,
      "nonCurrentLiabilities": 488725540.57,
      "shortLoan": 310019694.11,
      "longLoan": 424995824.86,
      "bondsPayable": null,
      "totalEquity": 924581225.04,
      "totalEquityYoY": 17.58,
      "parentEquity": 787960374.33,
      "minorityEquity": 136620850.71,
      "debtRatio": 71.95,
      "currentRatio": 1.3,
      "equityMultiplier": 3.57
    },
    {
      "reportDate": "2024-06-30",
      "reportName": "2024中报",
      "totalAssets": 3663208544.28,
      "totalAssetsYoY": -13.66,
      "currentAssets": 2826986212.32,
      "nonCurrentAssets": 836222331.96,
      "monetaryFunds": 656390380.86,
      "accountsReceivable": 691553007.14,
      "inventory": 1015113989.98,
      "fixedAsset": 410436994.83,
      "intangibleAsset": 55148954.5,
      "goodwill": 308369819.24,
      "totalLiabilities": 2739791565.91,
      "totalLiabilitiesYoY": -9.39,
      "currentLiabilities": 2175639722.97,
      "nonCurrentLiabilities": 564151842.94,
      "shortLoan": 400291004.18,
      "longLoan": 505004435.97,
      "bondsPayable": null,
      "totalEquity": 923416978.37,
      "totalEquityYoY": -24.27,
      "parentEquity": 793695415.13,
      "minorityEquity": 129721563.24,
      "debtRatio": 74.79,
      "currentRatio": 1.3,
      "equityMultiplier": 3.97
    },
    {
      "reportDate": "2024-03-31",
      "reportName": "2024一季报",
      "totalAssets": 3747686352.7,
      "totalAssetsYoY": -6.68,
      "currentAssets": 2891754137.1,
      "nonCurrentAssets": 855932215.6,
      "monetaryFunds": 504315430.72,
      "accountsReceivable": 642166090.51,
      "inventory": 1014144662.08,
      "fixedAsset": 358654786.51,
      "intangibleAsset": 56791978.15,
      "goodwill": 308369819.24,
      "totalLiabilities": 2803513320.11,
      "totalLiabilitiesYoY": 1.09,
      "currentLiabilities": 2215912305.29,
      "nonCurrentLiabilities": 587601014.82,
      "shortLoan": 385327736.05,
      "longLoan": 516560779.88,
      "bondsPayable": null,
      "totalEquity": 944173032.59,
      "totalEquityYoY": -24.02,
      "parentEquity": 795678376.49,
      "minorityEquity": 148494656.1,
      "debtRatio": 74.81,
      "currentRatio": 1.3,
      "equityMultiplier": 3.97
    },
    {
      "reportDate": "2023-12-31",
      "reportName": "2023年报",
      "totalAssets": 3620525071.7,
      "totalAssetsYoY": -2.07,
      "currentAssets": 2802180119.01,
      "nonCurrentAssets": 818344952.69,
      "monetaryFunds": 516631353.76,
      "accountsReceivable": 498574555.45,
      "inventory": 1063345148.13,
      "fixedAsset": 341015096.38,
      "intangibleAsset": 57629408.81,
      "goodwill": 308369819.24,
      "totalLiabilities": 2668088253.04,
      "totalLiabilitiesYoY": 7.21,
      "currentLiabilities": 2119819048.69,
      "nonCurrentLiabilities": 548269204.35,
      "shortLoan": 227174180.56,
      "longLoan": 476380790.97,
      "bondsPayable": null,
      "totalEquity": 952436818.66,
      "totalEquityYoY": -21.18,
      "parentEquity": 814213627.67,
      "minorityEquity": 138223190.99,
      "debtRatio": 73.69,
      "currentRatio": 1.32,
      "equityMultiplier": 3.8
    },
    {
      "reportDate": "2023-09-30",
      "reportName": "2023三季报",
      "totalAssets": 4194278583.83,
      "totalAssetsYoY": 12.0,
      "currentAssets": 3315229269.64,
      "nonCurrentAssets": 879049314.19,
      "monetaryFunds": 631608759.05,
      "accountsReceivable": 560985796.87,
      "inventory": 1497207310.59,
      "fixedAsset": 276004926.16,
      "intangibleAsset": 70424049.77,
      "goodwill": 308364819.24,
      "totalLiabilities": 3407911147.9,
      "totalLiabilitiesYoY": 28.5,
      "currentLiabilities": 2827471494.3,
      "nonCurrentLiabilities": 580439653.6,
      "shortLoan": 507723513.9,
      "longLoan": 567994430.83,
      "bondsPayable": null,
      "totalEquity": 786367435.93,
      "totalEquityYoY": -28.04,
      "parentEquity": 673745059.88,
      "minorityEquity": 112622376.05,
      "debtRatio": 81.25,
      "currentRatio": 1.17,
      "equityMultiplier": 5.33
    },
    {
      "reportDate": "2023-06-30",
      "reportName": "2023中报",
      "totalAssets": 4242886860.54,
      "totalAssetsYoY": 27.52,
      "currentAssets": 3365985180.88,
      "nonCurrentAssets": 876901679.66,
      "monetaryFunds": 705077545.37,
      "accountsReceivable": 658195839.7,
      "inventory": 1396103387.26,
      "fixedAsset": 281720807.51,
      "intangibleAsset": 71364933.77,
      "goodwill": 308364819.24,
      "totalLiabilities": 3023570176.73,
      "totalLiabilitiesYoY": 30.62,
      "currentLiabilities": 2682322960.54,
      "nonCurrentLiabilities": 341247216.19,
      "shortLoan": 297427963.89,
      "longLoan": 322389535.0,
      "bondsPayable": null,
      "totalEquity": 1219316683.81,
      "totalEquityYoY": 20.44,
      "parentEquity": 996285673.13,
      "minorityEquity": 223031010.68,
      "debtRatio": 71.26,
      "currentRatio": 1.25,
      "equityMultiplier": 3.48
    },
    {
      "reportDate": "2023-03-31",
      "reportName": "2023一季报",
      "totalAssets": 4015940990.74,
      "totalAssetsYoY": 107.53,
      "currentAssets": 3193751577.01,
      "nonCurrentAssets": 822189413.73,
      "monetaryFunds": 762446057.45,
      "accountsReceivable": 624030666.86,
      "inventory": 1190227936.55,
      "fixedAsset": 240752847.46,
      "intangibleAsset": 72442212.37,
      "goodwill": 308364819.24,
      "totalLiabilities": 2773205377.6,
      "totalLiabilitiesYoY": 158.29,
      "currentLiabilities": 2469872965.14,
      "nonCurrentLiabilities": 303332412.46,
      "shortLoan": 305584017.89,
      "longLoan": 275847083.33,
      "bondsPayable": null,
      "totalEquity": 1242735613.14,
      "totalEquityYoY": 44.27,
      "parentEquity": 1014533307.26,
      "minorityEquity": 228202305.88,
      "debtRatio": 69.05,
      "currentRatio": 1.29,
      "equityMultiplier": 3.23
    },
    {
      "reportDate": "2022-12-31",
      "reportName": "2022年报",
      "totalAssets": 3696935565.86,
      "totalAssetsYoY": 105.92,
      "currentAssets": 2946895259.54,
      "nonCurrentAssets": 750040306.32,
      "monetaryFunds": 712748043.89,
      "accountsReceivable": 611583942.99,
      "inventory": 964054324.33,
      "fixedAsset": 231245203.89,
      "intangibleAsset": 73441858.62,
      "goodwill": 308364819.24,
      "totalLiabilities": 2488600331.87,
      "totalLiabilitiesYoY": 173.03,
      "currentLiabilities": 2242738969.05,
      "nonCurrentLiabilities": 245861362.82,
      "shortLoan": 275223679.24,
      "longLoan": 225231250.0,
      "bondsPayable": null,
      "totalEquity": 1208335233.99,
      "totalEquityYoY": 36.72,
      "parentEquity": 996801046.41,
      "minorityEquity": 211534187.58,
      "debtRatio": 67.32,
      "currentRatio": 1.31,
      "equityMultiplier": 3.06
    },
    {
      "reportDate": "2022-09-30",
      "reportName": "2022三季报",
      "totalAssets": 3744859533.17,
      "totalAssetsYoY": 95.67,
      "currentAssets": 2963303229.1,
      "nonCurrentAssets": 781556304.07,
      "monetaryFunds": 473906770.72,
      "accountsReceivable": 676828841.12,
      "inventory": 1101287824.29,
      "fixedAsset": 319010109.24,
      "intangibleAsset": 77698435.62,
      "goodwill": 313908040.06,
      "totalLiabilities": 2652097599.79,
      "totalLiabilitiesYoY": 154.82,
      "currentLiabilities": 2343426197.63,
      "nonCurrentLiabilities": 308671402.16,
      "shortLoan": 276544138.91,
      "longLoan": 270036944.45,
      "bondsPayable": null,
      "totalEquity": 1092761933.38,
      "totalEquityYoY": 25.16,
      "parentEquity": 939231686.04,
      "minorityEquity": 153530247.34,
      "debtRatio": 70.82,
      "currentRatio": 1.26,
      "equityMultiplier": 3.43
    },
    {
      "reportDate": "2022-06-30",
      "reportName": "2022中报",
      "totalAssets": 3327123561.66,
      "totalAssetsYoY": 81.13,
      "currentAssets": 2539682516.8,
      "nonCurrentAssets": 787441044.86,
      "monetaryFunds": 553799794.98,
      "accountsReceivable": 555836383.34,
      "inventory": 997759667.8,
      "fixedAsset": 323968978.28,
      "intangibleAsset": 82285822.93,
      "goodwill": 313908040.06,
      "totalLiabilities": 2314753224.82,
      "totalLiabilitiesYoY": 142.96,
      "currentLiabilities": 2242801768.76,
      "nonCurrentLiabilities": 71951456.06,
      "shortLoan": 362762916.69,
      "longLoan": 35036944.45,
      "bondsPayable": null,
      "totalEquity": 1012370336.84,
      "totalEquityYoY": 14.51,
      "parentEquity": 885056534.67,
      "minorityEquity": 127313802.17,
      "debtRatio": 69.57,
      "currentRatio": 1.13,
      "equityMultiplier": 3.29
    },
    {
      "reportDate": "2022-03-31",
      "reportName": "2022一季报",
      "totalAssets": 1935090590.39,
      "totalAssetsYoY": 14.29,
      "currentAssets": 1548538462.05,
      "nonCurrentAssets": 386552128.34,
      "monetaryFunds": 369901078.48,
      "accountsReceivable": 454265541.45,
      "inventory": 510774748.28,
      "fixedAsset": 313059490.24,
      "intangibleAsset": 28861176.24,
      "goodwill": 6028982.03,
      "totalLiabilities": 1073678295.38,
      "totalLiabilitiesYoY": 32.08,
      "currentLiabilities": 1027257433.88,
      "nonCurrentLiabilities": 46420861.5,
      "shortLoan": 367000000.0,
      "longLoan": 35000000.0,
      "bondsPayable": null,
      "totalEquity": 861412295.01,
      "totalEquityYoY": -2.13,
      "parentEquity": 846721201.6,
      "minorityEquity": 14691093.41,
      "debtRatio": 55.48,
      "currentRatio": 1.51,
      "equityMultiplier": 2.25
    },
    {
      "reportDate": "2021-12-31",
      "reportName": "2021年报",
      "totalAssets": 1795300496.21,
      "totalAssetsYoY": 13.78,
      "currentAssets": 1403783315.03,
      "nonCurrentAssets": 391517181.18,
      "monetaryFunds": 284566306.77,
      "accountsReceivable": 511188358.7,
      "inventory": 430058847.43,
      "fixedAsset": 323322721.39,
      "intangibleAsset": 25110768.42,
      "goodwill": 6028982.03,
      "totalLiabilities": 911466099.32,
      "totalLiabilitiesYoY": 35.99,
      "currentLiabilities": 858928700.42,
      "nonCurrentLiabilities": 52537398.9,
      "shortLoan": 274907004.01,
      "longLoan": 40042222.22,
      "bondsPayable": null,
      "totalEquity": 883834396.89,
      "totalEquityYoY": -2.62,
      "parentEquity": 868641741.79,
      "minorityEquity": 15192655.1,
      "debtRatio": 50.77,
      "currentRatio": 1.63,
      "equityMultiplier": 2.03
    },
    {
      "reportDate": "2021-09-30",
      "reportName": "2021三季报",
      "totalAssets": 1913831808.04,
      "totalAssetsYoY": 20.02,
      "currentAssets": 1465431099.35,
      "nonCurrentAssets": 448400708.69,
      "monetaryFunds": 395509370.62,
      "accountsReceivable": 385176262.24,
      "inventory": 499523179.1,
      "fixedAsset": 316836628.59,
      "intangibleAsset": 53948823.19,
      "goodwill": 2153226.95,
      "totalLiabilities": 1040763421.27,
      "totalLiabilitiesYoY": 49.01,
      "currentLiabilities": 990258137.05,
      "nonCurrentLiabilities": 50505284.22,
      "shortLoan": 444710320.0,
      "longLoan": 40000000.0,
      "bondsPayable": null,
      "totalEquity": 873068386.77,
      "totalEquityYoY": -2.58,
      "parentEquity": 855539080.02,
      "minorityEquity": 17529306.75,
      "debtRatio": 54.38,
      "currentRatio": 1.48,
      "equityMultiplier": 2.19
    },
    {
      "reportDate": "2021-06-30",
      "reportName": "2021中报",
      "totalAssets": 1836863783.21,
      "totalAssetsYoY": 15.4,
      "currentAssets": 1382883996.03,
      "nonCurrentAssets": 453979787.18,
      "monetaryFunds": 286867797.03,
      "accountsReceivable": 346572891.81,
      "inventory": 458123050.87,
      "fixedAsset": 311921803.06,
      "intangibleAsset": 54295894.39,
      "goodwill": 2153226.95,
      "totalLiabilities": 952737202.63,
      "totalLiabilitiesYoY": 39.16,
      "currentLiabilities": 896818359.24,
      "nonCurrentLiabilities": 55918843.39,
      "shortLoan": 409811340.0,
      "longLoan": 45000000.0,
      "bondsPayable": null,
      "totalEquity": 884126580.58,
      "totalEquityYoY": -2.54,
      "parentEquity": 865367247.58,
      "minorityEquity": 18759333.0,
      "debtRatio": 51.87,
      "currentRatio": 1.54,
      "equityMultiplier": 2.08
    }
  ],
  "cashflow": [
    {
      "reportDate": "2026-03-31",
      "reportName": "2026一季报",
      "salesCash": 209447161.94,
      "operatingCashInflow": 223957564.41,
      "operatingCashOutflow": 213836471.98,
      "netOperatingCash": 10121092.43,
      "netOperatingCashYoY": -78.39,
      "investCashInflow": 80743241.4,
      "investCashOutflow": 89609481.27,
      "netInvestCash": -8866239.87,
      "netInvestCashYoY": 94.58,
      "fixedAssetInvest": null,
      "financeCashInflow": 115500000.0,
      "financeCashOutflow": 176967825.54,
      "netFinanceCash": -61467825.54,
      "netFinanceCashYoY": -332.7,
      "netCashIncrease": -60826041.26
    },
    {
      "reportDate": "2025-12-31",
      "reportName": "2025年报",
      "salesCash": 749685015.29,
      "operatingCashInflow": 851443021.53,
      "operatingCashOutflow": 691671624.3,
      "netOperatingCash": 159771397.23,
      "netOperatingCashYoY": 546.67,
      "investCashInflow": 713193959.84,
      "investCashOutflow": 858457969.92,
      "netInvestCash": -145264010.08,
      "netInvestCashYoY": -392.84,
      "fixedAssetInvest": null,
      "financeCashInflow": 453278792.42,
      "financeCashOutflow": 714652843.4,
      "netFinanceCash": -261374050.98,
      "netFinanceCashYoY": -253.21,
      "netCashIncrease": -246581944.12
    },
    {
      "reportDate": "2025-09-30",
      "reportName": "2025三季报",
      "salesCash": 571483851.43,
      "operatingCashInflow": 709480854.0,
      "operatingCashOutflow": 642439389.43,
      "netOperatingCash": 67041464.57,
      "netOperatingCashYoY": 395.62,
      "investCashInflow": 388079546.24,
      "investCashOutflow": 481761778.47,
      "netInvestCash": -93682232.23,
      "netInvestCashYoY": -799.32,
      "fixedAssetInvest": null,
      "financeCashInflow": 388660941.63,
      "financeCashOutflow": 501708497.38,
      "netFinanceCash": -113047555.75,
      "netFinanceCashYoY": -156.09,
      "netCashIncrease": -139484626.35
    },
    {
      "reportDate": "2025-06-30",
      "reportName": "2025中报",
      "salesCash": 449538619.3,
      "operatingCashInflow": 571525889.5,
      "operatingCashOutflow": 458806290.14,
      "netOperatingCash": 112719599.36,
      "netOperatingCashYoY": 298.09,
      "investCashInflow": 242200887.99,
      "investCashOutflow": 326939792.36,
      "netInvestCash": -84738904.37,
      "netInvestCashYoY": -477.02,
      "fixedAssetInvest": null,
      "financeCashInflow": 363105540.53,
      "financeCashOutflow": 455986833.99,
      "netFinanceCash": -92881293.46,
      "netFinanceCashYoY": -201.02,
      "netCashIncrease": -64703083.6
    },
    {
      "reportDate": "2025-03-31",
      "reportName": "2025一季报",
      "salesCash": 153924935.03,
      "operatingCashInflow": 271133174.31,
      "operatingCashOutflow": 224296374.21,
      "netOperatingCash": 46836800.1,
      "netOperatingCashYoY": 242.17,
      "investCashInflow": 58344396.49,
      "investCashOutflow": 221833531.34,
      "netInvestCash": -163489134.85,
      "netInvestCashYoY": -68.84,
      "fixedAssetInvest": null,
      "financeCashInflow": 186000000.0,
      "financeCashOutflow": 159584696.67,
      "netFinanceCash": 26415303.33,
      "netFinanceCashYoY": -80.17,
      "netCashIncrease": -89979643.53
    },
    {
      "reportDate": "2024-12-31",
      "reportName": "2024年报",
      "salesCash": 967753043.57,
      "operatingCashInflow": 1089967146.83,
      "operatingCashOutflow": 1065260526.18,
      "netOperatingCash": 24706620.65,
      "netOperatingCashYoY": 476.77,
      "investCashInflow": 277296579.26,
      "investCashOutflow": 227690986.82,
      "netInvestCash": 49605592.44,
      "netInvestCashYoY": 881.76,
      "fixedAssetInvest": null,
      "financeCashInflow": 637390000.0,
      "financeCashOutflow": 711390191.68,
      "netFinanceCash": -74000191.68,
      "netFinanceCashYoY": 15.22,
      "netCashIncrease": 1554241.56
    },
    {
      "reportDate": "2024-09-30",
      "reportName": "2024三季报",
      "salesCash": 758681135.62,
      "operatingCashInflow": 834951369.74,
      "operatingCashOutflow": 857629630.87,
      "netOperatingCash": -22678261.13,
      "netOperatingCashYoY": 86.63,
      "investCashInflow": 166237881.5,
      "investCashOutflow": 152841657.5,
      "netInvestCash": 13396224.0,
      "netInvestCashYoY": 103.46,
      "fixedAssetInvest": null,
      "financeCashInflow": 546032118.0,
      "financeCashOutflow": 590175604.88,
      "netFinanceCash": -44143486.88,
      "netFinanceCashYoY": -110.34,
      "netCashIncrease": -51689614.26
    },
    {
      "reportDate": "2024-06-30",
      "reportName": "2024中报",
      "salesCash": 617183418.27,
      "operatingCashInflow": 643221769.17,
      "operatingCashOutflow": 700124061.55,
      "netOperatingCash": -56902292.38,
      "netOperatingCashYoY": 74.63,
      "investCashInflow": 154260200.6,
      "investCashOutflow": 131784353.06,
      "netInvestCash": 22475847.54,
      "netInvestCashYoY": 23.19,
      "fixedAssetInvest": null,
      "financeCashInflow": 500167647.5,
      "financeCashOutflow": 408226446.33,
      "netFinanceCash": 91941201.17,
      "netFinanceCashYoY": 68.31,
      "netCashIncrease": 59295790.88
    },
    {
      "reportDate": "2024-03-31",
      "reportName": "2024一季报",
      "salesCash": 255477580.67,
      "operatingCashInflow": 322471374.61,
      "operatingCashOutflow": 355414551.98,
      "netOperatingCash": -32943177.37,
      "netOperatingCashYoY": 87.59,
      "investCashInflow": 2514527.28,
      "investCashOutflow": 99342890.96,
      "netInvestCash": -96828363.68,
      "netInvestCashYoY": -256.08,
      "fixedAssetInvest": null,
      "financeCashInflow": 250177647.5,
      "financeCashOutflow": 116955844.37,
      "netFinanceCash": 133221803.13,
      "netFinanceCashYoY": 178.83,
      "netCashIncrease": 4126486.86
    },
    {
      "reportDate": "2023-12-31",
      "reportName": "2023年报",
      "salesCash": 1537550038.89,
      "operatingCashInflow": 1931326383.34,
      "operatingCashOutflow": 1927042773.75,
      "netOperatingCash": 4283609.59,
      "netOperatingCashYoY": -93.25,
      "investCashInflow": 277580574.75,
      "investCashOutflow": 272527853.05,
      "netInvestCash": 5052721.7,
      "netInvestCashYoY": 105.89,
      "fixedAssetInvest": null,
      "financeCashInflow": 958879491.38,
      "financeCashOutflow": 1046165633.96,
      "netFinanceCash": -87286142.58,
      "netFinanceCashYoY": -133.56,
      "netCashIncrease": -70342442.75
    },
    {
      "reportDate": "2023-09-30",
      "reportName": "2023三季报",
      "salesCash": 1689934181.39,
      "operatingCashInflow": 1876212101.95,
      "operatingCashOutflow": 2045883338.59,
      "netOperatingCash": -169671236.64,
      "netOperatingCashYoY": -456.04,
      "investCashInflow": 148461932.4,
      "investCashOutflow": 535747780.31,
      "netInvestCash": -387285847.91,
      "netInvestCashYoY": -247.31,
      "fixedAssetInvest": null,
      "financeCashInflow": 814912300.0,
      "financeCashOutflow": 387883574.32,
      "netFinanceCash": 427028725.68,
      "netFinanceCashYoY": 105.22,
      "netCashIncrease": -128284237.56
    },
    {
      "reportDate": "2023-06-30",
      "reportName": "2023中报",
      "salesCash": 940001021.89,
      "operatingCashInflow": 1089218040.96,
      "operatingCashOutflow": 1313534662.74,
      "netOperatingCash": -224316621.78,
      "netOperatingCashYoY": -14.04,
      "investCashInflow": 147577361.12,
      "investCashOutflow": 129331763.02,
      "netInvestCash": 18245598.1,
      "netInvestCashYoY": -93.89,
      "fixedAssetInvest": null,
      "financeCashInflow": 279412300.0,
      "financeCashOutflow": 224786300.95,
      "netFinanceCash": 54625999.05,
      "netFinanceCashYoY": -26.29,
      "netCashIncrease": -150793803.65
    },
    {
      "reportDate": "2023-03-31",
      "reportName": "2023一季报",
      "salesCash": 436295822.91,
      "operatingCashInflow": 500433450.06,
      "operatingCashOutflow": 765833209.85,
      "netOperatingCash": -265399759.79,
      "netOperatingCashYoY": -156.19,
      "investCashInflow": 147561783.34,
      "investCashOutflow": 85525952.76,
      "netInvestCash": 62035830.58,
      "netInvestCashYoY": 64.66,
      "fixedAssetInvest": null,
      "financeCashInflow": 157912300.0,
      "financeCashOutflow": 110133754.44,
      "netFinanceCash": 47778545.56,
      "netFinanceCashYoY": -42.38,
      "netCashIncrease": -157003751.07
    },
    {
      "reportDate": "2022-12-31",
      "reportName": "2022年报",
      "salesCash": 1743448340.88,
      "operatingCashInflow": 1840030537.24,
      "operatingCashOutflow": 1776583783.51,
      "netOperatingCash": 63446753.73,
      "netOperatingCashYoY": 151.69,
      "investCashInflow": 337938504.04,
      "investCashOutflow": 423768204.32,
      "netInvestCash": -85829700.28,
      "netInvestCashYoY": -152.4,
      "fixedAssetInvest": null,
      "financeCashInflow": 772883555.97,
      "financeCashOutflow": 512819566.09,
      "netFinanceCash": 260063989.88,
      "netFinanceCashYoY": 673.79,
      "netCashIncrease": 268619574.69
    },
    {
      "reportDate": "2022-09-30",
      "reportName": "2022三季报",
      "salesCash": 1056205990.61,
      "operatingCashInflow": 1166848180.32,
      "operatingCashOutflow": 1119192502.95,
      "netOperatingCash": 47655677.37,
      "netOperatingCashYoY": 139.69,
      "investCashInflow": 211142401.62,
      "investCashOutflow": 322651044.57,
      "netInvestCash": -111508642.95,
      "netInvestCashYoY": -273.54,
      "fixedAssetInvest": null,
      "financeCashInflow": 498000000.0,
      "financeCashOutflow": 289918943.58,
      "netFinanceCash": 208081056.42,
      "netFinanceCashYoY": 30.46,
      "netCashIncrease": 162398385.75
    },
    {
      "reportDate": "2022-06-30",
      "reportName": "2022中报",
      "salesCash": 665070278.86,
      "operatingCashInflow": 696564536.14,
      "operatingCashOutflow": 893266532.74,
      "netOperatingCash": -196701996.6,
      "netOperatingCashYoY": -108.4,
      "investCashInflow": 120191779.78,
      "investCashOutflow": -178562582.7,
      "netInvestCash": 298754362.48,
      "netInvestCashYoY": 1258.67,
      "fixedAssetInvest": null,
      "financeCashInflow": 230000000.0,
      "financeCashOutflow": 155891142.55,
      "netFinanceCash": 74108857.45,
      "netFinanceCashYoY": -44.8,
      "netCashIncrease": 181699846.41
    },
    {
      "reportDate": "2022-03-31",
      "reportName": "2022一季报",
      "salesCash": 317537307.53,
      "operatingCashInflow": 330685259.81,
      "operatingCashOutflow": 434278294.54,
      "netOperatingCash": -103593034.73,
      "netOperatingCashYoY": -23.22,
      "investCashInflow": 46406365.11,
      "investCashOutflow": 8730245.64,
      "netInvestCash": 37676119.47,
      "netInvestCashYoY": 30.02,
      "fixedAssetInvest": null,
      "financeCashInflow": 181000000.0,
      "financeCashOutflow": 98076076.74,
      "netFinanceCash": 82923923.26,
      "netFinanceCashYoY": -34.46,
      "netCashIncrease": 12927986.12
    },
    {
      "reportDate": "2021-12-31",
      "reportName": "2021年报",
      "salesCash": 663032988.67,
      "operatingCashInflow": 710869835.79,
      "operatingCashOutflow": 833608725.81,
      "netOperatingCash": -122738890.02,
      "netOperatingCashYoY": -277.92,
      "investCashInflow": 699741486.94,
      "investCashOutflow": 535948923.0,
      "netInvestCash": 163792563.94,
      "netInvestCashYoY": 468.66,
      "fixedAssetInvest": null,
      "financeCashInflow": 477654150.0,
      "financeCashOutflow": 522977840.23,
      "netFinanceCash": -45323690.23,
      "netFinanceCashYoY": 73.09,
      "netCashIncrease": -7882907.27
    },
    {
      "reportDate": "2021-09-30",
      "reportName": "2021三季报",
      "salesCash": 604454089.69,
      "operatingCashInflow": 640376880.87,
      "operatingCashOutflow": 760459562.82,
      "netOperatingCash": -120082681.95,
      "netOperatingCashYoY": -193.22,
      "investCashInflow": 462973351.64,
      "investCashOutflow": 398719049.36,
      "netInvestCash": 64254302.28,
      "netInvestCashYoY": -57.44,
      "fixedAssetInvest": null,
      "financeCashInflow": 375654150.0,
      "financeCashOutflow": 216162193.33,
      "netFinanceCash": 159491956.67,
      "netFinanceCashYoY": 203.09,
      "netCashIncrease": 102339363.61
    },
    {
      "reportDate": "2021-06-30",
      "reportName": "2021中报",
      "salesCash": 388368666.39,
      "operatingCashInflow": 410173678.43,
      "operatingCashOutflow": 504559011.01,
      "netOperatingCash": -94385332.58,
      "netOperatingCashYoY": -1935.36,
      "investCashInflow": 254798213.42,
      "investCashOutflow": 280582450.41,
      "netInvestCash": -25784236.99,
      "netInvestCashYoY": -124.63,
      "fixedAssetInvest": null,
      "financeCashInflow": 180654150.0,
      "financeCashOutflow": 46403749.84,
      "netFinanceCash": 134250400.16,
      "netFinanceCashYoY": 181.43,
      "netCashIncrease": 11737109.22
    }
  ],
  "shareholder": {
    "top10Holders": [
      {
        "endDate": "2026-03-31",
        "rank": 1,
        "name": "科云新材料有限公司",
        "sharesType": "流通A股",
        "shares": 58240000.0,
        "sharesRatio": 28.0,
        "change": "不变"
      },
      {
        "endDate": "2026-03-31",
        "rank": 2,
        "name": "东台华昇晖投资有限公司",
        "sharesType": "流通A股",
        "shares": 21320000.0,
        "sharesRatio": 10.25,
        "change": "不变"
      },
      {
        "endDate": "2026-03-31",
        "rank": 3,
        "name": "江苏道森投资有限公司",
        "sharesType": "流通A股",
        "shares": 18190000.0,
        "sharesRatio": 8.75,
        "change": "不变"
      },
      {
        "endDate": "2026-03-31",
        "rank": 4,
        "name": "西藏诺德科技有限公司",
        "sharesType": "流通A股",
        "shares": 7207200.0,
        "sharesRatio": 3.47,
        "change": "不变"
      },
      {
        "endDate": "2026-03-31",
        "rank": 5,
        "name": "朱岳海",
        "sharesType": "流通A股",
        "shares": 5401322.0,
        "sharesRatio": 2.6,
        "change": "1202200"
      },
      {
        "endDate": "2026-03-31",
        "rank": 6,
        "name": "朱凯伦",
        "sharesType": "流通A股",
        "shares": 1999300.0,
        "sharesRatio": 0.96,
        "change": "200000"
      },
      {
        "endDate": "2026-03-31",
        "rank": 7,
        "name": "朱凯逸",
        "sharesType": "流通A股",
        "shares": 1558100.0,
        "sharesRatio": 0.75,
        "change": "新进"
      },
      {
        "endDate": "2026-03-31",
        "rank": 8,
        "name": "香港中央结算有限公司",
        "sharesType": "流通A股",
        "shares": 1241230.0,
        "sharesRatio": 0.6,
        "change": "新进"
      },
      {
        "endDate": "2026-03-31",
        "rank": 9,
        "name": "余士保",
        "sharesType": "流通A股",
        "shares": 1157900.0,
        "sharesRatio": 0.56,
        "change": "新进"
      },
      {
        "endDate": "2026-03-31",
        "rank": 10,
        "name": "李立权",
        "sharesType": "流通A股",
        "shares": 980000.0,
        "sharesRatio": 0.47,
        "change": "新进"
      }
    ],
    "top10CircHolders": [
      {
        "endDate": "2026-03-31",
        "rank": 1,
        "name": "科云新材料有限公司",
        "sharesType": "A股",
        "shares": 58240000.0,
        "sharesRatio": 28.0,
        "change": "不变",
        "type": "其它"
      },
      {
        "endDate": "2026-03-31",
        "rank": 2,
        "name": "东台华昇晖投资有限公司",
        "sharesType": "A股",
        "shares": 21320000.0,
        "sharesRatio": 10.25,
        "change": "不变",
        "type": "投资公司"
      },
      {
        "endDate": "2026-03-31",
        "rank": 3,
        "name": "江苏道森投资有限公司",
        "sharesType": "A股",
        "shares": 18190000.0,
        "sharesRatio": 8.745192307692,
        "change": "不变",
        "type": "投资公司"
      },
      {
        "endDate": "2026-03-31",
        "rank": 4,
        "name": "西藏诺德科技有限公司",
        "sharesType": "A股",
        "shares": 7207200.0,
        "sharesRatio": 3.465,
        "change": "不变",
        "type": "其它"
      },
      {
        "endDate": "2026-03-31",
        "rank": 5,
        "name": "朱岳海",
        "sharesType": "A股",
        "shares": 5401322.0,
        "sharesRatio": 2.596789423077,
        "change": "1202200",
        "type": "个人"
      },
      {
        "endDate": "2026-03-31",
        "rank": 6,
        "name": "朱凯伦",
        "sharesType": "A股",
        "shares": 1999300.0,
        "sharesRatio": 0.961201923077,
        "change": "200000",
        "type": "个人"
      },
      {
        "endDate": "2026-03-31",
        "rank": 7,
        "name": "朱凯逸",
        "sharesType": "A股",
        "shares": 1558100.0,
        "sharesRatio": 0.749086538462,
        "change": "新进",
        "type": "个人"
      },
      {
        "endDate": "2026-03-31",
        "rank": 8,
        "name": "香港中央结算有限公司",
        "sharesType": "A股",
        "shares": 1241230.0,
        "sharesRatio": 0.596745192308,
        "change": "新进",
        "type": "其它"
      },
      {
        "endDate": "2026-03-31",
        "rank": 9,
        "name": "余士保",
        "sharesType": "A股",
        "shares": 1157900.0,
        "sharesRatio": 0.556682692308,
        "change": "新进",
        "type": "个人"
      },
      {
        "endDate": "2026-03-31",
        "rank": 10,
        "name": "李立权",
        "sharesType": "A股",
        "shares": 980000.0,
        "sharesRatio": 0.471153846154,
        "change": "新进",
        "type": "个人"
      }
    ],
    "holderCountHistory": [
      {
        "endDate": "2026-03-31",
        "count": 17463.0,
        "changeRatio": 17.2013,
        "avgShares": 11910.0,
        "avgHoldAmount": 454043.406058524,
        "holdFocus": "较集中",
        "price": 38.12
      },
      {
        "endDate": "2025-12-31",
        "count": 14900.0,
        "changeRatio": -26.6443,
        "avgShares": 13959.0,
        "avgHoldAmount": 680816.10738255,
        "holdFocus": "较集中",
        "price": 48.77
      },
      {
        "endDate": "2025-09-30",
        "count": 20312.0,
        "changeRatio": 53.2287,
        "avgShares": 10240.0,
        "avgHoldAmount": 502591.571484837,
        "holdFocus": "较集中",
        "price": 49.08
      },
      {
        "endDate": "2025-06-30",
        "count": 13256.0,
        "changeRatio": 53.16,
        "avgShares": 15691.0,
        "avgHoldAmount": 396538.9129965,
        "holdFocus": "较集中",
        "price": 25.2717299552
      },
      {
        "endDate": "2025-03-31",
        "count": 8655.0,
        "changeRatio": -8.6929,
        "avgShares": 24032.0,
        "avgHoldAmount": 814016.391779827,
        "holdFocus": "非常集中",
        "price": 33.8716916868
      },
      {
        "endDate": "2024-12-31",
        "count": 9479.0,
        "changeRatio": 8.2819,
        "avgShares": 21943.0,
        "avgHoldAmount": 552138.355168267,
        "holdFocus": "非常集中",
        "price": 25.16211283
      },
      {
        "endDate": "2024-09-30",
        "count": 8754.0,
        "changeRatio": -8.3735,
        "avgShares": 23760.0,
        "avgHoldAmount": 510257.962070825,
        "holdFocus": "非常集中",
        "price": 21.474991346
      },
      {
        "endDate": "2024-06-30",
        "count": 9554.0,
        "changeRatio": -1.8189,
        "avgShares": 21770.0,
        "avgHoldAmount": 433904.162779987,
        "holdFocus": "非常集中",
        "price": 19.9303864
      },
      {
        "endDate": "2024-03-31",
        "count": 9731.0,
        "changeRatio": 3.0281,
        "avgShares": 21374.0,
        "avgHoldAmount": 491460.260169274,
        "holdFocus": "非常集中",
        "price": 22.9923066909
      },
      {
        "endDate": "2023-12-31",
        "count": 9445.0,
        "changeRatio": 5.9094,
        "avgShares": 22022.0,
        "avgHoldAmount": 575438.126849762,
        "holdFocus": "非常集中",
        "price": 26.129870712
      }
    ],
    "institutionalHoldings": [
      {
        "reportDate": "2026-03-31",
        "totalOrgs": 5.0,
        "totalShares": 106198430.0,
        "totalRatio": 51.0569375
      },
      {
        "reportDate": "2026-03-31",
        "totalOrgs": 5.0,
        "totalShares": 106198430.0,
        "totalRatio": 51.0569375
      }
    ],
    "fundHoldings": [
      {
        "reportDate": "2025-12-31",
        "fundCode": "015967",
        "fundName": "永赢半导体产业智选混合发起A",
        "shares": 5000000.0,
        "value": 243850000.0,
        "ratio": 2.40384615,
        "navRatio": 4.17
      },
      {
        "reportDate": "2025-12-31",
        "fundCode": "020001",
        "fundName": "国泰金鹰增长灵活配置混合",
        "shares": 1945100.0,
        "value": 94862527.0,
        "ratio": 0.93514423,
        "navRatio": 7.76
      },
      {
        "reportDate": "2025-12-31",
        "fundCode": "009804",
        "fundName": "国泰研究优势混合A",
        "shares": 1090200.0,
        "value": 53169054.0,
        "ratio": 0.52413462,
        "navRatio": 7.86
      },
      {
        "reportDate": "2025-12-31",
        "fundCode": "007872",
        "fundName": "金信稳健策略混合A",
        "shares": 1060000.0,
        "value": 51696200.0,
        "ratio": 0.50961538,
        "navRatio": 4.04
      },
      {
        "reportDate": "2025-12-31",
        "fundCode": "012445",
        "fundName": "华富新能源股票型发起式A",
        "shares": 674300.0,
        "value": 32885611.0,
        "ratio": 0.32418269,
        "navRatio": 0.79
      },
      {
        "reportDate": "2025-12-31",
        "fundCode": "003745",
        "fundName": "广发多元新兴股票",
        "shares": 524000.0,
        "value": 25555480.0,
        "ratio": 0.25192308,
        "navRatio": 1.2
      },
      {
        "reportDate": "2025-12-31",
        "fundCode": "012967",
        "fundName": "广发行业严选三年持有期混合A",
        "shares": 392800.0,
        "value": 19156856.0,
        "ratio": 0.18884615,
        "navRatio": 0.33
      },
      {
        "reportDate": "2025-12-31",
        "fundCode": "013851",
        "fundName": "中信建投低碳成长混合A",
        "shares": 350000.0,
        "value": 17069500.0,
        "ratio": 0.16826923,
        "navRatio": 2.94
      },
      {
        "reportDate": "2025-12-31",
        "fundCode": "009805",
        "fundName": "国泰医药健康股票A",
        "shares": 348692.0,
        "value": 17005708.84,
        "ratio": 0.16764038,
        "navRatio": 2.85
      },
      {
        "reportDate": "2025-12-31",
        "fundCode": "160215",
        "fundName": "国泰价值经典灵活配置混合(LOF)",
        "shares": 327800.0,
        "value": 15986806.0,
        "ratio": 0.15759615,
        "navRatio": 7.65
      }
    ],
    "dividends": [
      {
        "noticeDate": "2025-04-26",
        "reportDate": "2024-12-31",
        "bonusPer10": 1,
        "stockBonusPer10": null,
        "convertPer10": null,
        "status": "实施分配"
      },
      {
        "noticeDate": "2024-04-20",
        "reportDate": "2023-12-31",
        "bonusPer10": 1.5,
        "stockBonusPer10": null,
        "convertPer10": null,
        "status": "实施分配"
      },
      {
        "noticeDate": "2021-04-30",
        "reportDate": "2020-12-31",
        "bonusPer10": 0.07,
        "stockBonusPer10": null,
        "convertPer10": null,
        "status": "实施分配"
      },
      {
        "noticeDate": "2020-04-28",
        "reportDate": "2019-12-31",
        "bonusPer10": 5,
        "stockBonusPer10": null,
        "convertPer10": null,
        "status": "实施分配"
      },
      {
        "noticeDate": "2019-04-16",
        "reportDate": "2018-12-31",
        "bonusPer10": 5,
        "stockBonusPer10": null,
        "convertPer10": null,
        "status": "实施分配"
      },
      {
        "noticeDate": "2018-03-30",
        "reportDate": "2017-12-31",
        "bonusPer10": 1,
        "stockBonusPer10": null,
        "convertPer10": null,
        "status": "实施分配"
      },
      {
        "noticeDate": "2016-04-23",
        "reportDate": "2015-12-31",
        "bonusPer10": 1,
        "stockBonusPer10": null,
        "convertPer10": null,
        "status": "实施分配"
      }
    ]
  },
  "quote": {
    "code": "603800",
    "name": "洪田股份",
    "price": 80.62,
    "change": -0.71,
    "changePct": -0.87,
    "open": 81.0,
    "high": 81.8,
    "low": 78.71,
    "prevClose": 81.33,
    "volume": 74070,
    "amount": 59646.0,
    "totalMV": 16769000000.0,
    "circMV": 16769000000.0,
    "pe": 705.98,
    "pb": 21.2,
    "turnover": 3.56,
    "fetchTime": "2026-06-19T00:06:14"
  }
}